{
  "_meta": {
    "l1Category": "문구/오피스",
    "generatedAt": "2026-04-03T04:48:18.854Z",
    "profileCount": 18,
    "mode": "fallback"
  },
  "profiles": {
    "문구/오피스>오피스>미술>화방용품": {
      "displayName": "미술 화방용품 외",
      "parentGroup": "문구/오피스>오피스>미술",
      "variables": {
        "효과1": [
          "내구성",
          "편의성",
          "수납력",
          "디자인",
          "정확성",
          "생산성",
          "보존력",
          "휴대성",
          "효율성",
          "안정감",
          "정리력",
          "활용도",
          "심미성",
          "실용성",
          "가독성"
        ],
        "효과2": [
          "작업효율",
          "깔끔함",
          "정리정돈",
          "편리함",
          "심미성",
          "오래감",
          "가성비",
          "활용도",
          "실용성",
          "세련됨"
        ],
        "성분": [
          "공예철사",
          "노란고무줄/고무밴드",
          "고무찰흙",
          "글라스데코",
          "기타학습만들기재료",
          "눈알",
          "부채만들기",
          "북아트재료"
        ],
        "성분2": [
          "프리미엄",
          "고급",
          "특수"
        ],
        "사용법": [
          "책상 위에 정리하여",
          "필요할 때 꺼내어",
          "파일에 분류하여 보관",
          "다이어리와 함께",
          "회의 시 활용하여",
          "서류와 함께 보관",
          "작업 중 가볍게",
          "업무에 활용하여"
        ],
        "사용감": [
          "깔끔한",
          "고급스러운",
          "가벼운",
          "견고한",
          "심플한",
          "세련된",
          "깨끗한",
          "단정한",
          "실용적인"
        ],
        "추천대상": [
          "학생",
          "직장인",
          "수험생",
          "디자이너",
          "작가",
          "교사",
          "프리랜서",
          "기획자",
          "사무직",
          "대학생",
          "회사원"
        ],
        "카테고리": [
          "화방용품",
          "오피스",
          "공예철사",
          "노란고무줄/고무밴드",
          "고무찰흙",
          "글라스데코"
        ],
        "기간": [
          "1주일",
          "한 달",
          "한 학기",
          "1년"
        ],
        "인증": [
          "KC인증",
          "환경마크",
          "FSC인증",
          "ISO인증",
          "안전확인"
        ]
      },
      "forbiddenTerms": [
        "세차",
        "광택",
        "발수",
        "세정력",
        "탈취",
        "살균",
        "토크",
        "절단력",
        "드릴",
        "윤활",
        "면역력",
        "복용",
        "영양제",
        "건강기능식품",
        "1정",
        "섭취",
        "논스틱",
        "인덕션",
        "프라이팬",
        "중약불",
        "보온력",
        "크림",
        "에센스",
        "립스틱",
        "강아지사료",
        "고양이사료",
        "오메가3",
        "홍삼",
        "김치",
        "된장",
        "한우",
        "파운데이션",
        "샴푸",
        "기저귀",
        "타이어",
        "마스카라"
      ]
    },
    "문구/오피스>오피스>사무기기": {
      "displayName": "오피스 사무기기 외",
      "parentGroup": "문구/오피스>오피스",
      "variables": {
        "효과1": [
          "내구성",
          "편의성",
          "수납력",
          "디자인",
          "정확성",
          "생산성",
          "보존력",
          "휴대성",
          "효율성",
          "안정감",
          "정리력",
          "활용도",
          "심미성",
          "실용성",
          "가독성"
        ],
        "효과2": [
          "작업효율",
          "깔끔함",
          "정리정돈",
          "편리함",
          "심미성",
          "오래감",
          "가성비",
          "활용도",
          "실용성",
          "세련됨"
        ],
        "성분": [
          "세단기/파쇄기",
          "기타재단기소모품",
          "재단기",
          "재단기날",
          "기타제본기소모품",
          "제본기",
          "제본와이어링",
          "제본테이프"
        ],
        "성분2": [
          "프리미엄",
          "고급",
          "특수"
        ],
        "사용법": [
          "책상 위에 정리하여",
          "필요할 때 꺼내어",
          "파일에 분류하여 보관",
          "다이어리와 함께",
          "회의 시 활용하여",
          "서류와 함께 보관",
          "작업 중 가볍게",
          "업무에 활용하여"
        ],
        "사용감": [
          "깔끔한",
          "고급스러운",
          "가벼운",
          "견고한",
          "심플한",
          "세련된",
          "깨끗한",
          "단정한",
          "실용적인"
        ],
        "추천대상": [
          "학생",
          "직장인",
          "수험생",
          "디자이너",
          "작가",
          "교사",
          "프리랜서",
          "기획자",
          "사무직",
          "대학생",
          "회사원"
        ],
        "카테고리": [
          "사무기기",
          "오피스",
          "세단기/파쇄기",
          "기타재단기소모품",
          "재단기",
          "재단기날"
        ],
        "기간": [
          "1주일",
          "한 달",
          "한 학기",
          "1년"
        ],
        "인증": [
          "KC인증",
          "환경마크",
          "FSC인증",
          "ISO인증",
          "안전확인"
        ]
      },
      "forbiddenTerms": [
        "세차",
        "광택",
        "발수",
        "세정력",
        "탈취",
        "살균",
        "토크",
        "절단력",
        "드릴",
        "윤활",
        "면역력",
        "복용",
        "영양제",
        "건강기능식품",
        "1정",
        "섭취",
        "논스틱",
        "인덕션",
        "프라이팬",
        "중약불",
        "보온력",
        "크림",
        "에센스",
        "립스틱",
        "강아지사료",
        "고양이사료",
        "오메가3",
        "홍삼",
        "김치",
        "된장",
        "한우",
        "파운데이션",
        "샴푸",
        "기저귀",
        "타이어",
        "마스카라"
      ]
    },
    "문구/오피스>오피스>사무용품": {
      "displayName": "오피스 사무용품 외",
      "parentGroup": "문구/오피스>오피스",
      "variables": {
        "효과1": [
          "내구성",
          "편의성",
          "수납력",
          "디자인",
          "정확성",
          "생산성",
          "보존력",
          "휴대성",
          "효율성",
          "안정감",
          "정리력",
          "활용도",
          "심미성",
          "실용성",
          "가독성"
        ],
        "효과2": [
          "작업효율",
          "깔끔함",
          "정리정돈",
          "편리함",
          "심미성",
          "오래감",
          "가성비",
          "활용도",
          "실용성",
          "세련됨"
        ],
        "성분": [
          "공학용계산기",
          "일반계산기",
          "프린터계산기",
          "다이모/라벨기",
          "다이모리필테이프",
          "라벨카트리지/테이프",
          "데스크매트/패드",
          "데스크멀티박스"
        ],
        "성분2": [
          "프리미엄",
          "고급",
          "특수"
        ],
        "사용법": [
          "책상 위에 정리하여",
          "필요할 때 꺼내어",
          "파일에 분류하여 보관",
          "다이어리와 함께",
          "회의 시 활용하여",
          "서류와 함께 보관",
          "작업 중 가볍게",
          "업무에 활용하여"
        ],
        "사용감": [
          "깔끔한",
          "고급스러운",
          "가벼운",
          "견고한",
          "심플한",
          "세련된",
          "깨끗한",
          "단정한",
          "실용적인"
        ],
        "추천대상": [
          "학생",
          "직장인",
          "수험생",
          "디자이너",
          "작가",
          "교사",
          "프리랜서",
          "기획자",
          "사무직",
          "대학생",
          "회사원"
        ],
        "카테고리": [
          "사무용품",
          "오피스",
          "공학용계산기",
          "일반계산기",
          "프린터계산기",
          "다이모/라벨기"
        ],
        "기간": [
          "1주일",
          "한 달",
          "한 학기",
          "1년"
        ],
        "인증": [
          "KC인증",
          "환경마크",
          "FSC인증",
          "ISO인증",
          "안전확인"
        ]
      },
      "forbiddenTerms": [
        "세차",
        "광택",
        "발수",
        "세정력",
        "탈취",
        "살균",
        "토크",
        "절단력",
        "드릴",
        "윤활",
        "면역력",
        "복용",
        "영양제",
        "건강기능식품",
        "1정",
        "섭취",
        "논스틱",
        "인덕션",
        "프라이팬",
        "중약불",
        "보온력",
        "크림",
        "에센스",
        "립스틱",
        "강아지사료",
        "고양이사료",
        "오메가3",
        "홍삼",
        "김치",
        "된장",
        "한우",
        "파운데이션",
        "샴푸",
        "기저귀",
        "타이어",
        "마스카라"
      ]
    },
    "문구/오피스>오피스>학용품>가위": {
      "displayName": "학용품 가위 외",
      "parentGroup": "문구/오피스>오피스>학용품",
      "variables": {
        "효과1": [
          "내구성",
          "편의성",
          "수납력",
          "디자인",
          "정확성",
          "생산성",
          "보존력",
          "휴대성",
          "효율성",
          "안정감",
          "정리력",
          "활용도",
          "심미성",
          "실용성",
          "가독성"
        ],
        "효과2": [
          "작업효율",
          "깔끔함",
          "정리정돈",
          "편리함",
          "심미성",
          "오래감",
          "가성비",
          "활용도",
          "실용성",
          "세련됨"
        ],
        "성분": [
          "사무용가위",
          "유아동안전가위",
          "핑킹가위",
          "열선",
          "열선커터기",
          "칼날 리필/통",
          "커터매트/커팅매트",
          "커터칼"
        ],
        "성분2": [
          "프리미엄",
          "고급",
          "특수"
        ],
        "사용법": [
          "책상 위에 정리하여",
          "필요할 때 꺼내어",
          "파일에 분류하여 보관",
          "다이어리와 함께",
          "회의 시 활용하여",
          "서류와 함께 보관",
          "작업 중 가볍게",
          "업무에 활용하여"
        ],
        "사용감": [
          "깔끔한",
          "고급스러운",
          "가벼운",
          "견고한",
          "심플한",
          "세련된",
          "깨끗한",
          "단정한",
          "실용적인"
        ],
        "추천대상": [
          "학생",
          "직장인",
          "수험생",
          "디자이너",
          "작가",
          "교사",
          "프리랜서",
          "기획자",
          "사무직",
          "대학생",
          "회사원"
        ],
        "카테고리": [
          "가위",
          "오피스",
          "사무용가위",
          "유아동안전가위",
          "핑킹가위",
          "열선"
        ],
        "기간": [
          "1주일",
          "한 달",
          "한 학기",
          "1년"
        ],
        "인증": [
          "KC인증",
          "환경마크",
          "FSC인증",
          "ISO인증",
          "안전확인"
        ]
      },
      "forbiddenTerms": [
        "세차",
        "광택",
        "발수",
        "세정력",
        "탈취",
        "살균",
        "토크",
        "절단력",
        "드릴",
        "윤활",
        "면역력",
        "복용",
        "영양제",
        "건강기능식품",
        "1정",
        "섭취",
        "논스틱",
        "인덕션",
        "프라이팬",
        "중약불",
        "보온력",
        "크림",
        "에센스",
        "립스틱",
        "강아지사료",
        "고양이사료",
        "오메가3",
        "홍삼",
        "김치",
        "된장",
        "한우",
        "파운데이션",
        "샴푸",
        "기저귀",
        "타이어",
        "마스카라"
      ]
    },
    "문구/오피스>오피스>학용품>과목별준비물": {
      "displayName": "학용품 과목별준비물 외",
      "parentGroup": "문구/오피스>오피스>학용품",
      "variables": {
        "효과1": [
          "내구성",
          "편의성",
          "수납력",
          "디자인",
          "정확성",
          "생산성",
          "보존력",
          "휴대성",
          "효율성",
          "안정감",
          "정리력",
          "활용도",
          "심미성",
          "실용성",
          "가독성"
        ],
        "효과2": [
          "작업효율",
          "깔끔함",
          "정리정돈",
          "편리함",
          "심미성",
          "오래감",
          "가성비",
          "활용도",
          "실용성",
          "세련됨"
        ],
        "성분": [
          "생물실험세트",
          "화석/유물 발굴키트",
          "화석만들기키트",
          "LED과학재료",
          "고무동력기",
          "글라이더",
          "기초로봇",
          "물로켓/에어로켓"
        ],
        "성분2": [
          "프리미엄",
          "고급",
          "특수"
        ],
        "사용법": [
          "책상 위에 정리하여",
          "필요할 때 꺼내어",
          "파일에 분류하여 보관",
          "다이어리와 함께",
          "회의 시 활용하여",
          "서류와 함께 보관",
          "작업 중 가볍게",
          "업무에 활용하여"
        ],
        "사용감": [
          "깔끔한",
          "고급스러운",
          "가벼운",
          "견고한",
          "심플한",
          "세련된",
          "깨끗한",
          "단정한",
          "실용적인"
        ],
        "추천대상": [
          "학생",
          "직장인",
          "수험생",
          "디자이너",
          "작가",
          "교사",
          "프리랜서",
          "기획자",
          "사무직",
          "대학생",
          "회사원"
        ],
        "카테고리": [
          "과목별준비물",
          "오피스",
          "생물실험세트",
          "화석/유물 발굴키트",
          "화석만들기키트",
          "LED과학재료"
        ],
        "기간": [
          "1주일",
          "한 달",
          "한 학기",
          "1년"
        ],
        "인증": [
          "KC인증",
          "환경마크",
          "FSC인증",
          "ISO인증",
          "안전확인"
        ]
      },
      "forbiddenTerms": [
        "세차",
        "광택",
        "발수",
        "세정력",
        "탈취",
        "살균",
        "토크",
        "절단력",
        "드릴",
        "윤활",
        "면역력",
        "복용",
        "영양제",
        "건강기능식품",
        "1정",
        "섭취",
        "논스틱",
        "인덕션",
        "프라이팬",
        "중약불",
        "보온력",
        "크림",
        "에센스",
        "립스틱",
        "강아지사료",
        "고양이사료",
        "오메가3",
        "홍삼",
        "김치",
        "된장",
        "한우",
        "파운데이션",
        "샴푸",
        "기저귀",
        "타이어",
        "마스카라"
      ]
    },
    "문구/오피스>오피스>학용품>노트": {
      "displayName": "학용품 노트 외",
      "parentGroup": "문구/오피스>오피스>학용품",
      "variables": {
        "효과1": [
          "내구성",
          "편의성",
          "수납력",
          "디자인",
          "정확성",
          "생산성",
          "보존력",
          "휴대성",
          "효율성",
          "안정감",
          "정리력",
          "활용도",
          "심미성",
          "실용성",
          "가독성"
        ],
        "효과2": [
          "작업효율",
          "깔끔함",
          "정리정돈",
          "편리함",
          "심미성",
          "오래감",
          "가성비",
          "활용도",
          "실용성",
          "세련됨"
        ],
        "성분": [
          "노트커버/패드",
          "일반노트",
          "가계부/캐쉬북",
          "기도/필사노트",
          "기타기록노트",
          "독서기록장",
          "레시피북",
          "일기장"
        ],
        "성분2": [
          "프리미엄",
          "고급",
          "특수"
        ],
        "사용법": [
          "책상 위에 정리하여",
          "필요할 때 꺼내어",
          "파일에 분류하여 보관",
          "다이어리와 함께",
          "회의 시 활용하여",
          "서류와 함께 보관",
          "작업 중 가볍게",
          "업무에 활용하여"
        ],
        "사용감": [
          "깔끔한",
          "고급스러운",
          "가벼운",
          "견고한",
          "심플한",
          "세련된",
          "깨끗한",
          "단정한",
          "실용적인"
        ],
        "추천대상": [
          "학생",
          "직장인",
          "수험생",
          "디자이너",
          "작가",
          "교사",
          "프리랜서",
          "기획자",
          "사무직",
          "대학생",
          "회사원"
        ],
        "카테고리": [
          "노트",
          "오피스",
          "노트커버/패드",
          "일반노트",
          "가계부/캐쉬북",
          "기도/필사노트"
        ],
        "기간": [
          "1주일",
          "한 달",
          "한 학기",
          "1년"
        ],
        "인증": [
          "KC인증",
          "환경마크",
          "FSC인증",
          "ISO인증",
          "안전확인"
        ]
      },
      "forbiddenTerms": [
        "세차",
        "광택",
        "발수",
        "세정력",
        "탈취",
        "살균",
        "토크",
        "절단력",
        "드릴",
        "윤활",
        "면역력",
        "복용",
        "영양제",
        "건강기능식품",
        "1정",
        "섭취",
        "논스틱",
        "인덕션",
        "프라이팬",
        "중약불",
        "보온력",
        "크림",
        "에센스",
        "립스틱",
        "강아지사료",
        "고양이사료",
        "오메가3",
        "홍삼",
        "김치",
        "된장",
        "한우",
        "파운데이션",
        "샴푸",
        "기저귀",
        "타이어",
        "마스카라"
      ]
    },
    "문구/오피스>오피스>학용품>봉투": {
      "displayName": "학용품 봉투 외",
      "parentGroup": "문구/오피스>오피스>학용품",
      "variables": {
        "효과1": [
          "내구성",
          "편의성",
          "수납력",
          "디자인",
          "정확성",
          "생산성",
          "보존력",
          "휴대성",
          "효율성",
          "안정감",
          "정리력",
          "활용도",
          "심미성",
          "실용성",
          "가독성"
        ],
        "효과2": [
          "작업효율",
          "깔끔함",
          "정리정돈",
          "편리함",
          "심미성",
          "오래감",
          "가성비",
          "활용도",
          "실용성",
          "세련됨"
        ],
        "성분": [
          "경조사봉투",
          "서류/각대봉투",
          "안전에어봉투",
          "예단봉투",
          "용돈봉투",
          "카드봉투/엽서봉투",
          "택배봉투",
          "규격우편봉투"
        ],
        "성분2": [
          "프리미엄",
          "고급",
          "특수"
        ],
        "사용법": [
          "책상 위에 정리하여",
          "필요할 때 꺼내어",
          "파일에 분류하여 보관",
          "다이어리와 함께",
          "회의 시 활용하여",
          "서류와 함께 보관",
          "작업 중 가볍게",
          "업무에 활용하여"
        ],
        "사용감": [
          "깔끔한",
          "고급스러운",
          "가벼운",
          "견고한",
          "심플한",
          "세련된",
          "깨끗한",
          "단정한",
          "실용적인"
        ],
        "추천대상": [
          "학생",
          "직장인",
          "수험생",
          "디자이너",
          "작가",
          "교사",
          "프리랜서",
          "기획자",
          "사무직",
          "대학생",
          "회사원"
        ],
        "카테고리": [
          "봉투",
          "오피스",
          "경조사봉투",
          "서류/각대봉투",
          "안전에어봉투",
          "예단봉투"
        ],
        "기간": [
          "1주일",
          "한 달",
          "한 학기",
          "1년"
        ],
        "인증": [
          "KC인증",
          "환경마크",
          "FSC인증",
          "ISO인증",
          "안전확인"
        ]
      },
      "forbiddenTerms": [
        "세차",
        "광택",
        "발수",
        "세정력",
        "탈취",
        "살균",
        "토크",
        "절단력",
        "드릴",
        "윤활",
        "면역력",
        "복용",
        "영양제",
        "건강기능식품",
        "1정",
        "섭취",
        "논스틱",
        "인덕션",
        "프라이팬",
        "중약불",
        "보온력",
        "크림",
        "에센스",
        "립스틱",
        "강아지사료",
        "고양이사료",
        "오메가3",
        "홍삼",
        "김치",
        "된장",
        "한우",
        "파운데이션",
        "샴푸",
        "기저귀",
        "타이어",
        "마스카라"
      ]
    },
    "문구/오피스>오피스>학용품>스탬프": {
      "displayName": "학용품 스탬프 외",
      "parentGroup": "문구/오피스>오피스>학용품",
      "variables": {
        "효과1": [
          "내구성",
          "편의성",
          "수납력",
          "디자인",
          "정확성",
          "생산성",
          "보존력",
          "휴대성",
          "효율성",
          "안정감",
          "정리력",
          "활용도",
          "심미성",
          "실용성",
          "가독성"
        ],
        "효과2": [
          "작업효율",
          "깔끔함",
          "정리정돈",
          "편리함",
          "심미성",
          "오래감",
          "가성비",
          "활용도",
          "실용성",
          "세련됨"
        ],
        "성분": [
          "네임스탬프",
          "데코/팬시스탬프",
          "사무용스탬프",
          "스탬프잉크/패드",
          "정보보안스탬프/롤러",
          "칭찬스탬프",
          "씰/씰링",
          "씰왁스"
        ],
        "성분2": [
          "프리미엄",
          "고급",
          "특수"
        ],
        "사용법": [
          "책상 위에 정리하여",
          "필요할 때 꺼내어",
          "파일에 분류하여 보관",
          "다이어리와 함께",
          "회의 시 활용하여",
          "서류와 함께 보관",
          "작업 중 가볍게",
          "업무에 활용하여"
        ],
        "사용감": [
          "깔끔한",
          "고급스러운",
          "가벼운",
          "견고한",
          "심플한",
          "세련된",
          "깨끗한",
          "단정한",
          "실용적인"
        ],
        "추천대상": [
          "학생",
          "직장인",
          "수험생",
          "디자이너",
          "작가",
          "교사",
          "프리랜서",
          "기획자",
          "사무직",
          "대학생",
          "회사원"
        ],
        "카테고리": [
          "스탬프",
          "오피스",
          "네임스탬프",
          "데코/팬시스탬프",
          "사무용스탬프",
          "스탬프잉크/패드"
        ],
        "기간": [
          "1주일",
          "한 달",
          "한 학기",
          "1년"
        ],
        "인증": [
          "KC인증",
          "환경마크",
          "FSC인증",
          "ISO인증",
          "안전확인"
        ]
      },
      "forbiddenTerms": [
        "세차",
        "광택",
        "발수",
        "세정력",
        "탈취",
        "살균",
        "토크",
        "절단력",
        "드릴",
        "윤활",
        "면역력",
        "복용",
        "영양제",
        "건강기능식품",
        "1정",
        "섭취",
        "논스틱",
        "인덕션",
        "프라이팬",
        "중약불",
        "보온력",
        "크림",
        "에센스",
        "립스틱",
        "강아지사료",
        "고양이사료",
        "오메가3",
        "홍삼",
        "김치",
        "된장",
        "한우",
        "파운데이션",
        "샴푸",
        "기저귀",
        "타이어",
        "마스카라"
      ]
    },
    "문구/오피스>오피스>학용품>스테이플러": {
      "displayName": "학용품 스테이플러",
      "parentGroup": "문구/오피스>오피스>학용품",
      "variables": {
        "효과1": [
          "내구성",
          "편의성",
          "수납력",
          "디자인",
          "정확성",
          "생산성",
          "보존력",
          "휴대성",
          "효율성",
          "안정감",
          "정리력",
          "활용도",
          "심미성",
          "실용성",
          "가독성"
        ],
        "효과2": [
          "작업효율",
          "깔끔함",
          "정리정돈",
          "편리함",
          "심미성",
          "오래감",
          "가성비",
          "활용도",
          "실용성",
          "세련됨"
        ],
        "성분": [
          "스테이플러",
          "스테이플러 리무버/제침기",
          "스테이플러 심",
          "모양펀치",
          "일반펀치"
        ],
        "성분2": [
          "프리미엄",
          "고급",
          "특수"
        ],
        "사용법": [
          "책상 위에 정리하여",
          "필요할 때 꺼내어",
          "파일에 분류하여 보관",
          "다이어리와 함께",
          "회의 시 활용하여",
          "서류와 함께 보관",
          "작업 중 가볍게",
          "업무에 활용하여"
        ],
        "사용감": [
          "깔끔한",
          "고급스러운",
          "가벼운",
          "견고한",
          "심플한",
          "세련된",
          "깨끗한",
          "단정한",
          "실용적인"
        ],
        "추천대상": [
          "학생",
          "직장인",
          "수험생",
          "디자이너",
          "작가",
          "교사",
          "프리랜서",
          "기획자",
          "사무직",
          "대학생",
          "회사원"
        ],
        "카테고리": [
          "스테이플러",
          "오피스",
          "스테이플러 리무버/제침기",
          "스테이플러 심",
          "모양펀치"
        ],
        "기간": [
          "1주일",
          "한 달",
          "한 학기",
          "1년"
        ],
        "인증": [
          "KC인증",
          "환경마크",
          "FSC인증",
          "ISO인증",
          "안전확인"
        ]
      },
      "forbiddenTerms": [
        "세차",
        "광택",
        "발수",
        "세정력",
        "탈취",
        "살균",
        "토크",
        "절단력",
        "드릴",
        "윤활",
        "면역력",
        "복용",
        "영양제",
        "건강기능식품",
        "1정",
        "섭취",
        "논스틱",
        "인덕션",
        "프라이팬",
        "중약불",
        "보온력",
        "크림",
        "에센스",
        "립스틱",
        "강아지사료",
        "고양이사료",
        "오메가3",
        "홍삼",
        "김치",
        "된장",
        "한우",
        "파운데이션",
        "샴푸",
        "기저귀",
        "타이어",
        "마스카라"
      ]
    },
    "문구/오피스>오피스>학용품>스티커": {
      "displayName": "학용품 스티커 외",
      "parentGroup": "문구/오피스>오피스>학용품",
      "variables": {
        "효과1": [
          "내구성",
          "편의성",
          "수납력",
          "디자인",
          "정확성",
          "생산성",
          "보존력",
          "휴대성",
          "효율성",
          "안정감",
          "정리력",
          "활용도",
          "심미성",
          "실용성",
          "가독성"
        ],
        "효과2": [
          "작업효율",
          "깔끔함",
          "정리정돈",
          "편리함",
          "심미성",
          "오래감",
          "가성비",
          "활용도",
          "실용성",
          "세련됨"
        ],
        "성분": [
          "보호필름견출지",
          "일반견출지",
          "네임스티커",
          "라벨스티커",
          "리폼스티커",
          "인덱스스티커/플래그",
          "칭찬스티커",
          "캐리어스티커/빅스티커"
        ],
        "성분2": [
          "프리미엄",
          "고급",
          "특수"
        ],
        "사용법": [
          "책상 위에 정리하여",
          "필요할 때 꺼내어",
          "파일에 분류하여 보관",
          "다이어리와 함께",
          "회의 시 활용하여",
          "서류와 함께 보관",
          "작업 중 가볍게",
          "업무에 활용하여"
        ],
        "사용감": [
          "깔끔한",
          "고급스러운",
          "가벼운",
          "견고한",
          "심플한",
          "세련된",
          "깨끗한",
          "단정한",
          "실용적인"
        ],
        "추천대상": [
          "학생",
          "직장인",
          "수험생",
          "디자이너",
          "작가",
          "교사",
          "프리랜서",
          "기획자",
          "사무직",
          "대학생",
          "회사원"
        ],
        "카테고리": [
          "스티커",
          "오피스",
          "보호필름견출지",
          "일반견출지",
          "네임스티커",
          "라벨스티커"
        ],
        "기간": [
          "1주일",
          "한 달",
          "한 학기",
          "1년"
        ],
        "인증": [
          "KC인증",
          "환경마크",
          "FSC인증",
          "ISO인증",
          "안전확인"
        ]
      },
      "forbiddenTerms": [
        "세차",
        "광택",
        "발수",
        "세정력",
        "탈취",
        "살균",
        "토크",
        "절단력",
        "드릴",
        "윤활",
        "면역력",
        "복용",
        "영양제",
        "건강기능식품",
        "1정",
        "섭취",
        "논스틱",
        "인덕션",
        "프라이팬",
        "중약불",
        "보온력",
        "크림",
        "에센스",
        "립스틱",
        "강아지사료",
        "고양이사료",
        "오메가3",
        "홍삼",
        "김치",
        "된장",
        "한우",
        "파운데이션",
        "샴푸",
        "기저귀",
        "타이어",
        "마스카라"
      ]
    },
    "문구/오피스>오피스>학용품>앨범": {
      "displayName": "학용품 앨범",
      "parentGroup": "문구/오피스>오피스>학용품",
      "variables": {
        "효과1": [
          "내구성",
          "편의성",
          "수납력",
          "디자인",
          "정확성",
          "생산성",
          "보존력",
          "휴대성",
          "효율성",
          "안정감",
          "정리력",
          "활용도",
          "심미성",
          "실용성",
          "가독성"
        ],
        "효과2": [
          "작업효율",
          "깔끔함",
          "정리정돈",
          "편리함",
          "심미성",
          "오래감",
          "가성비",
          "활용도",
          "실용성",
          "세련됨"
        ],
        "성분": [
          "기타스크랩북",
          "미니앨범/폴라로이드앨범",
          "일반포토앨범",
          "출산/성장앨범",
          "티켓/영화앨범"
        ],
        "성분2": [
          "프리미엄",
          "고급",
          "특수"
        ],
        "사용법": [
          "책상 위에 정리하여",
          "필요할 때 꺼내어",
          "파일에 분류하여 보관",
          "다이어리와 함께",
          "회의 시 활용하여",
          "서류와 함께 보관",
          "작업 중 가볍게",
          "업무에 활용하여"
        ],
        "사용감": [
          "깔끔한",
          "고급스러운",
          "가벼운",
          "견고한",
          "심플한",
          "세련된",
          "깨끗한",
          "단정한",
          "실용적인"
        ],
        "추천대상": [
          "학생",
          "직장인",
          "수험생",
          "디자이너",
          "작가",
          "교사",
          "프리랜서",
          "기획자",
          "사무직",
          "대학생",
          "회사원"
        ],
        "카테고리": [
          "앨범",
          "오피스",
          "기타스크랩북",
          "미니앨범/폴라로이드앨범",
          "일반포토앨범",
          "출산/성장앨범"
        ],
        "기간": [
          "1주일",
          "한 달",
          "한 학기",
          "1년"
        ],
        "인증": [
          "KC인증",
          "환경마크",
          "FSC인증",
          "ISO인증",
          "안전확인"
        ]
      },
      "forbiddenTerms": [
        "세차",
        "광택",
        "발수",
        "세정력",
        "탈취",
        "살균",
        "토크",
        "절단력",
        "드릴",
        "윤활",
        "면역력",
        "복용",
        "영양제",
        "건강기능식품",
        "1정",
        "섭취",
        "논스틱",
        "인덕션",
        "프라이팬",
        "중약불",
        "보온력",
        "크림",
        "에센스",
        "립스틱",
        "강아지사료",
        "고양이사료",
        "오메가3",
        "홍삼",
        "김치",
        "된장",
        "한우",
        "파운데이션",
        "샴푸",
        "기저귀",
        "타이어",
        "마스카라"
      ]
    },
    "문구/오피스>오피스>학용품>지우개": {
      "displayName": "학용품 지우개 외",
      "parentGroup": "문구/오피스>오피스>학용품",
      "variables": {
        "효과1": [
          "내구성",
          "편의성",
          "수납력",
          "디자인",
          "정확성",
          "생산성",
          "보존력",
          "휴대성",
          "효율성",
          "안정감",
          "정리력",
          "활용도",
          "심미성",
          "실용성",
          "가독성"
        ],
        "효과2": [
          "작업효율",
          "깔끔함",
          "정리정돈",
          "편리함",
          "심미성",
          "오래감",
          "가성비",
          "활용도",
          "실용성",
          "세련됨"
        ],
        "성분": [
          "수정액",
          "수정테이프",
          "미술용지우개",
          "샤프형지우개",
          "샤프형지우개리필",
          "일반지우개",
          "전동지우개",
          "전동지우개리필"
        ],
        "성분2": [
          "프리미엄",
          "고급",
          "특수"
        ],
        "사용법": [
          "책상 위에 정리하여",
          "필요할 때 꺼내어",
          "파일에 분류하여 보관",
          "다이어리와 함께",
          "회의 시 활용하여",
          "서류와 함께 보관",
          "작업 중 가볍게",
          "업무에 활용하여"
        ],
        "사용감": [
          "깔끔한",
          "고급스러운",
          "가벼운",
          "견고한",
          "심플한",
          "세련된",
          "깨끗한",
          "단정한",
          "실용적인"
        ],
        "추천대상": [
          "학생",
          "직장인",
          "수험생",
          "디자이너",
          "작가",
          "교사",
          "프리랜서",
          "기획자",
          "사무직",
          "대학생",
          "회사원"
        ],
        "카테고리": [
          "지우개",
          "오피스",
          "수정액",
          "수정테이프",
          "미술용지우개",
          "샤프형지우개"
        ],
        "기간": [
          "1주일",
          "한 달",
          "한 학기",
          "1년"
        ],
        "인증": [
          "KC인증",
          "환경마크",
          "FSC인증",
          "ISO인증",
          "안전확인"
        ]
      },
      "forbiddenTerms": [
        "세차",
        "광택",
        "발수",
        "세정력",
        "탈취",
        "살균",
        "토크",
        "절단력",
        "드릴",
        "윤활",
        "면역력",
        "복용",
        "영양제",
        "건강기능식품",
        "1정",
        "섭취",
        "논스틱",
        "인덕션",
        "프라이팬",
        "중약불",
        "보온력",
        "크림",
        "에센스",
        "립스틱",
        "강아지사료",
        "고양이사료",
        "오메가3",
        "홍삼",
        "김치",
        "된장",
        "한우",
        "파운데이션",
        "샴푸",
        "기저귀",
        "타이어",
        "마스카라"
      ]
    },
    "문구/오피스>오피스>학용품>카드": {
      "displayName": "학용품 카드 외",
      "parentGroup": "문구/오피스>오피스>학용품",
      "variables": {
        "효과1": [
          "내구성",
          "편의성",
          "수납력",
          "디자인",
          "정확성",
          "생산성",
          "보존력",
          "휴대성",
          "효율성",
          "안정감",
          "정리력",
          "활용도",
          "심미성",
          "실용성",
          "가독성"
        ],
        "효과2": [
          "작업효율",
          "깔끔함",
          "정리정돈",
          "편리함",
          "심미성",
          "오래감",
          "가성비",
          "활용도",
          "실용성",
          "세련됨"
        ],
        "성분": [
          "그림/일러스트엽서",
          "디자인패턴엽서",
          "타이포/캘리그라피엽서",
          "포토엽서",
          "드라이플라워카드",
          "연하장",
          "일반카드",
          "전통카드"
        ],
        "성분2": [
          "프리미엄",
          "고급",
          "특수"
        ],
        "사용법": [
          "책상 위에 정리하여",
          "필요할 때 꺼내어",
          "파일에 분류하여 보관",
          "다이어리와 함께",
          "회의 시 활용하여",
          "서류와 함께 보관",
          "작업 중 가볍게",
          "업무에 활용하여"
        ],
        "사용감": [
          "깔끔한",
          "고급스러운",
          "가벼운",
          "견고한",
          "심플한",
          "세련된",
          "깨끗한",
          "단정한",
          "실용적인"
        ],
        "추천대상": [
          "학생",
          "직장인",
          "수험생",
          "디자이너",
          "작가",
          "교사",
          "프리랜서",
          "기획자",
          "사무직",
          "대학생",
          "회사원"
        ],
        "카테고리": [
          "카드",
          "오피스",
          "그림/일러스트엽서",
          "디자인패턴엽서",
          "타이포/캘리그라피엽서",
          "포토엽서"
        ],
        "기간": [
          "1주일",
          "한 달",
          "한 학기",
          "1년"
        ],
        "인증": [
          "KC인증",
          "환경마크",
          "FSC인증",
          "ISO인증",
          "안전확인"
        ]
      },
      "forbiddenTerms": [
        "세차",
        "광택",
        "발수",
        "세정력",
        "탈취",
        "살균",
        "토크",
        "절단력",
        "드릴",
        "윤활",
        "면역력",
        "복용",
        "영양제",
        "건강기능식품",
        "1정",
        "섭취",
        "논스틱",
        "인덕션",
        "프라이팬",
        "중약불",
        "보온력",
        "크림",
        "에센스",
        "립스틱",
        "강아지사료",
        "고양이사료",
        "오메가3",
        "홍삼",
        "김치",
        "된장",
        "한우",
        "파운데이션",
        "샴푸",
        "기저귀",
        "타이어",
        "마스카라"
      ]
    },
    "문구/오피스>오피스>학용품>컴퍼스": {
      "displayName": "학용품 컴퍼스 외",
      "parentGroup": "문구/오피스>오피스>학용품",
      "variables": {
        "효과1": [
          "내구성",
          "편의성",
          "수납력",
          "디자인",
          "정확성",
          "생산성",
          "보존력",
          "휴대성",
          "효율성",
          "안정감",
          "정리력",
          "활용도",
          "심미성",
          "실용성",
          "가독성"
        ],
        "효과2": [
          "작업효율",
          "깔끔함",
          "정리정돈",
          "편리함",
          "심미성",
          "오래감",
          "가성비",
          "활용도",
          "실용성",
          "세련됨"
        ],
        "성분": [
          "겹자",
          "도형자/모양자",
          "삼각스케일",
          "각도기자/분도기",
          "삼각/각도기세트",
          "삼각자",
          "줄자",
          "직자/방안자"
        ],
        "성분2": [
          "프리미엄",
          "고급",
          "특수"
        ],
        "사용법": [
          "책상 위에 정리하여",
          "필요할 때 꺼내어",
          "파일에 분류하여 보관",
          "다이어리와 함께",
          "회의 시 활용하여",
          "서류와 함께 보관",
          "작업 중 가볍게",
          "업무에 활용하여"
        ],
        "사용감": [
          "깔끔한",
          "고급스러운",
          "가벼운",
          "견고한",
          "심플한",
          "세련된",
          "깨끗한",
          "단정한",
          "실용적인"
        ],
        "추천대상": [
          "학생",
          "직장인",
          "수험생",
          "디자이너",
          "작가",
          "교사",
          "프리랜서",
          "기획자",
          "사무직",
          "대학생",
          "회사원"
        ],
        "카테고리": [
          "컴퍼스",
          "오피스",
          "겹자",
          "도형자/모양자",
          "삼각스케일",
          "각도기자/분도기"
        ],
        "기간": [
          "1주일",
          "한 달",
          "한 학기",
          "1년"
        ],
        "인증": [
          "KC인증",
          "환경마크",
          "FSC인증",
          "ISO인증",
          "안전확인"
        ]
      },
      "forbiddenTerms": [
        "세차",
        "광택",
        "발수",
        "세정력",
        "탈취",
        "살균",
        "토크",
        "절단력",
        "드릴",
        "윤활",
        "면역력",
        "복용",
        "영양제",
        "건강기능식품",
        "1정",
        "섭취",
        "논스틱",
        "인덕션",
        "프라이팬",
        "중약불",
        "보온력",
        "크림",
        "에센스",
        "립스틱",
        "강아지사료",
        "고양이사료",
        "오메가3",
        "홍삼",
        "김치",
        "된장",
        "한우",
        "파운데이션",
        "샴푸",
        "기저귀",
        "타이어",
        "마스카라"
      ]
    },
    "문구/오피스>오피스>학용품>클립": {
      "displayName": "학용품 클립 외",
      "parentGroup": "문구/오피스>오피스>학용품",
      "variables": {
        "효과1": [
          "내구성",
          "편의성",
          "수납력",
          "디자인",
          "정확성",
          "생산성",
          "보존력",
          "휴대성",
          "효율성",
          "안정감",
          "정리력",
          "활용도",
          "심미성",
          "실용성",
          "가독성"
        ],
        "효과2": [
          "작업효율",
          "깔끔함",
          "정리정돈",
          "편리함",
          "심미성",
          "오래감",
          "가성비",
          "활용도",
          "실용성",
          "세련됨"
        ],
        "성분": [
          "날크립(클립)",
          "메모/문구자석",
          "압정",
          "일반크립(클립)",
          "철집게/더블크립(클립)",
          "카드링",
          "핀"
        ],
        "성분2": [
          "프리미엄",
          "고급",
          "특수"
        ],
        "사용법": [
          "책상 위에 정리하여",
          "필요할 때 꺼내어",
          "파일에 분류하여 보관",
          "다이어리와 함께",
          "회의 시 활용하여",
          "서류와 함께 보관",
          "작업 중 가볍게",
          "업무에 활용하여"
        ],
        "사용감": [
          "깔끔한",
          "고급스러운",
          "가벼운",
          "견고한",
          "심플한",
          "세련된",
          "깨끗한",
          "단정한",
          "실용적인"
        ],
        "추천대상": [
          "학생",
          "직장인",
          "수험생",
          "디자이너",
          "작가",
          "교사",
          "프리랜서",
          "기획자",
          "사무직",
          "대학생",
          "회사원"
        ],
        "카테고리": [
          "클립",
          "오피스",
          "날크립(클립)",
          "메모/문구자석",
          "압정",
          "일반크립(클립)"
        ],
        "기간": [
          "1주일",
          "한 달",
          "한 학기",
          "1년"
        ],
        "인증": [
          "KC인증",
          "환경마크",
          "FSC인증",
          "ISO인증",
          "안전확인"
        ]
      },
      "forbiddenTerms": [
        "세차",
        "광택",
        "발수",
        "세정력",
        "탈취",
        "살균",
        "토크",
        "절단력",
        "드릴",
        "윤활",
        "면역력",
        "복용",
        "영양제",
        "건강기능식품",
        "1정",
        "섭취",
        "논스틱",
        "인덕션",
        "프라이팬",
        "중약불",
        "보온력",
        "크림",
        "에센스",
        "립스틱",
        "강아지사료",
        "고양이사료",
        "오메가3",
        "홍삼",
        "김치",
        "된장",
        "한우",
        "파운데이션",
        "샴푸",
        "기저귀",
        "타이어",
        "마스카라"
      ]
    },
    "문구/오피스>오피스>학용품>테이프": {
      "displayName": "학용품 테이프 외",
      "parentGroup": "문구/오피스>오피스>학용품",
      "variables": {
        "효과1": [
          "내구성",
          "편의성",
          "수납력",
          "디자인",
          "정확성",
          "생산성",
          "보존력",
          "휴대성",
          "효율성",
          "안정감",
          "정리력",
          "활용도",
          "심미성",
          "실용성",
          "가독성"
        ],
        "효과2": [
          "작업효율",
          "깔끔함",
          "정리정돈",
          "편리함",
          "심미성",
          "오래감",
          "가성비",
          "활용도",
          "실용성",
          "세련됨"
        ],
        "성분": [
          "디자인마스킹테이프",
          "박스테이프",
          "셀로판테이프",
          "셀로판테이프리필",
          "양면테이프",
          "청테이프",
          "테이프커터/디스펜서",
          "패브릭테이프"
        ],
        "성분2": [
          "프리미엄",
          "고급",
          "특수"
        ],
        "사용법": [
          "책상 위에 정리하여",
          "필요할 때 꺼내어",
          "파일에 분류하여 보관",
          "다이어리와 함께",
          "회의 시 활용하여",
          "서류와 함께 보관",
          "작업 중 가볍게",
          "업무에 활용하여"
        ],
        "사용감": [
          "깔끔한",
          "고급스러운",
          "가벼운",
          "견고한",
          "심플한",
          "세련된",
          "깨끗한",
          "단정한",
          "실용적인"
        ],
        "추천대상": [
          "학생",
          "직장인",
          "수험생",
          "디자이너",
          "작가",
          "교사",
          "프리랜서",
          "기획자",
          "사무직",
          "대학생",
          "회사원"
        ],
        "카테고리": [
          "테이프",
          "오피스",
          "디자인마스킹테이프",
          "박스테이프",
          "셀로판테이프",
          "셀로판테이프리필"
        ],
        "기간": [
          "1주일",
          "한 달",
          "한 학기",
          "1년"
        ],
        "인증": [
          "KC인증",
          "환경마크",
          "FSC인증",
          "ISO인증",
          "안전확인"
        ]
      },
      "forbiddenTerms": [
        "세차",
        "광택",
        "발수",
        "세정력",
        "탈취",
        "살균",
        "토크",
        "절단력",
        "드릴",
        "윤활",
        "면역력",
        "복용",
        "영양제",
        "건강기능식품",
        "1정",
        "섭취",
        "논스틱",
        "인덕션",
        "프라이팬",
        "중약불",
        "보온력",
        "크림",
        "에센스",
        "립스틱",
        "강아지사료",
        "고양이사료",
        "오메가3",
        "홍삼",
        "김치",
        "된장",
        "한우",
        "파운데이션",
        "샴푸",
        "기저귀",
        "타이어",
        "마스카라"
      ]
    },
    "문구/오피스>오피스>학용품>포장": {
      "displayName": "학용품 포장 외",
      "parentGroup": "문구/오피스>오피스>학용품",
      "variables": {
        "효과1": [
          "내구성",
          "편의성",
          "수납력",
          "디자인",
          "정확성",
          "생산성",
          "보존력",
          "휴대성",
          "효율성",
          "안정감",
          "정리력",
          "활용도",
          "심미성",
          "실용성",
          "가독성"
        ],
        "효과2": [
          "작업효율",
          "깔끔함",
          "정리정돈",
          "편리함",
          "심미성",
          "오래감",
          "가성비",
          "활용도",
          "실용성",
          "세련됨"
        ],
        "성분": [
          "구김지",
          "스타핑",
          "도일리페이퍼",
          "선물보자기",
          "선물주머니",
          "쇼핑백",
          "리본빵끈/포장타이",
          "마끈/철끈"
        ],
        "성분2": [
          "프리미엄",
          "고급",
          "특수"
        ],
        "사용법": [
          "책상 위에 정리하여",
          "필요할 때 꺼내어",
          "파일에 분류하여 보관",
          "다이어리와 함께",
          "회의 시 활용하여",
          "서류와 함께 보관",
          "작업 중 가볍게",
          "업무에 활용하여"
        ],
        "사용감": [
          "깔끔한",
          "고급스러운",
          "가벼운",
          "견고한",
          "심플한",
          "세련된",
          "깨끗한",
          "단정한",
          "실용적인"
        ],
        "추천대상": [
          "학생",
          "직장인",
          "수험생",
          "디자이너",
          "작가",
          "교사",
          "프리랜서",
          "기획자",
          "사무직",
          "대학생",
          "회사원"
        ],
        "카테고리": [
          "포장",
          "오피스",
          "구김지",
          "스타핑",
          "도일리페이퍼",
          "선물보자기"
        ],
        "기간": [
          "1주일",
          "한 달",
          "한 학기",
          "1년"
        ],
        "인증": [
          "KC인증",
          "환경마크",
          "FSC인증",
          "ISO인증",
          "안전확인"
        ]
      },
      "forbiddenTerms": [
        "세차",
        "광택",
        "발수",
        "세정력",
        "탈취",
        "살균",
        "토크",
        "절단력",
        "드릴",
        "윤활",
        "면역력",
        "복용",
        "영양제",
        "건강기능식품",
        "1정",
        "섭취",
        "논스틱",
        "인덕션",
        "프라이팬",
        "중약불",
        "보온력",
        "크림",
        "에센스",
        "립스틱",
        "강아지사료",
        "고양이사료",
        "오메가3",
        "홍삼",
        "김치",
        "된장",
        "한우",
        "파운데이션",
        "샴푸",
        "기저귀",
        "타이어",
        "마스카라"
      ]
    },
    "문구/오피스>오피스>학용품>필기구": {
      "displayName": "학용품 필기구 외",
      "parentGroup": "문구/오피스>오피스>학용품",
      "variables": {
        "효과1": [
          "필기감",
          "발색",
          "정확성",
          "내구성",
          "그립감",
          "잉크지속",
          "선명도",
          "부드러움",
          "표현력",
          "가독성",
          "휴대성",
          "수납력",
          "정리력",
          "내구성"
        ],
        "효과2": [
          "작업효율",
          "깔끔함",
          "정리정돈",
          "편리함",
          "심미성",
          "오래감",
          "가성비",
          "활용도",
          "실용성",
          "세련됨"
        ],
        "성분": [
          "만년필",
          "만년필 세척 KIT",
          "만년필 펜촉",
          "만년필병잉크",
          "만년필카트리지",
          "만년필컨버터",
          "캘리그라피만년필",
          "붓펜"
        ],
        "성분2": [
          "프리미엄",
          "고급",
          "특수"
        ],
        "사용법": [
          "책상 위에 정리하여",
          "필기 시 가볍게 잡고",
          "파일에 분류하여 보관",
          "다이어리에 기록하며",
          "회의 시 메모하며",
          "노트에 정리하며",
          "업무에 활용하여"
        ],
        "사용감": [
          "깔끔한",
          "고급스러운",
          "가벼운",
          "견고한",
          "심플한",
          "세련된",
          "깨끗한",
          "단정한",
          "실용적인"
        ],
        "추천대상": [
          "학생",
          "직장인",
          "수험생",
          "디자이너",
          "작가",
          "교사",
          "프리랜서",
          "기획자",
          "사무직",
          "대학생",
          "회사원"
        ],
        "카테고리": [
          "필기구",
          "오피스",
          "만년필",
          "만년필 세척 KIT",
          "만년필 펜촉",
          "만년필병잉크"
        ],
        "기간": [
          "1주일",
          "한 달",
          "한 학기",
          "1년"
        ],
        "인증": [
          "KC인증",
          "환경마크",
          "FSC인증",
          "ISO인증",
          "안전확인"
        ]
      },
      "forbiddenTerms": [
        "세차",
        "광택",
        "발수",
        "세정력",
        "탈취",
        "살균",
        "토크",
        "절단력",
        "드릴",
        "윤활",
        "면역력",
        "복용",
        "영양제",
        "건강기능식품",
        "1정",
        "섭취",
        "논스틱",
        "인덕션",
        "프라이팬",
        "중약불",
        "보온력",
        "크림",
        "에센스",
        "립스틱",
        "강아지사료",
        "고양이사료",
        "오메가3",
        "홍삼",
        "김치",
        "된장",
        "한우",
        "파운데이션",
        "샴푸",
        "기저귀",
        "타이어",
        "마스카라"
      ]
    }
  }
}
